baseline/__about__.py
baseline/__init__.py
baseline/__main__.py
baseline/_baseline.py
baseline/_script.py
baseline-1.2.0.dist-info/DESCRIPTION.rst
baseline-1.2.0.dist-info/METADATA
baseline-1.2.0.dist-info/RECORD
baseline-1.2.0.dist-info/WHEEL
baseline-1.2.0.dist-info/entry_points.txt
baseline-1.2.0.dist-info/metadata.json
baseline-1.2.0.dist-info/top_level.txt
baseline-1.2.0.dist-info/zip-safe
