Metadata-Version: 2.0
Name: baseline
Version: 1.2.0
Summary: Easy string baseline.
Home-page: https://github.com/dmgass/baseline
Author: Dan Gass
Author-email: dan.gass@gmail.com
Maintainer: Dan Gass
Maintainer-email: dan.gass@gmail.com
License: MIT License ; http://opensource.org/licenses/MIT
Download-URL: https://github.com/dmgass/baseline
Keywords: compare baseline string test
Platform: any
Classifier: Development Status :: 5 - Production/Stable
Classifier: Intended Audience :: Developers
Classifier: License :: OSI Approved :: MIT License
Classifier: Operating System :: OS Independent
Classifier: Programming Language :: Python
Classifier: Programming Language :: Python :: 2
Classifier: Programming Language :: Python :: 2.7
Classifier: Programming Language :: Python :: 3
Classifier: Programming Language :: Python :: 3.6
Classifier: Programming Language :: Python :: 3.7
Classifier: Programming Language :: Python :: 3.8
Classifier: Programming Language :: Python :: 3.9
Classifier: Programming Language :: Python :: Implementation :: CPython
Classifier: Topic :: Text Processing
Requires-Python: !=3.0.*,!=3.1.*,!=3.2.*,!=3.3.*,>=2.7.0
Provides-Extra: doc
Provides-Extra: test
Requires-Dist: setuptools (>=39.0.1)
Requires-Dist: enum34 (>=1.1.6); python_version < "3.0"
Provides-Extra: doc
Requires-Dist: Sphinx (>=1.6.7); extra == 'doc'
Requires-Dist: sphinx-rtd-theme; extra == 'doc'
Requires-Dist: sphinxcontrib-programoutput; extra == 'doc'
Provides-Extra: test
Requires-Dist: nose; extra == 'test'
Provides-Extra: test
Requires-Dist: unittest2; python_version < "3.0" and extra == 'test'
Requires-Dist: mock (>=2.0.0); python_version < "3.0" and extra == 'test'
